README.md
setup.py
tests/test_cifar10_accuracy.py
tests/test_cifar2_accuracy.py
tests/test_class.py
tests/test_integration_cifar.py
tests/test_integration_clip.py
tests/test_integration_qnli.py
tests/test_jl.py
tests/test_jl_additional.py
tests/test_parallel.py
tests/test_rademacher.py
tests/test_rademacher_additional.py
trak/__init__.py
trak/gradient_computers.py
trak/modelout_functions.py
trak/projectors.py
trak/savers.py
trak/score_computers.py
trak/traker.py
trak/utils.py
traker.egg-info/PKG-INFO
traker.egg-info/SOURCES.txt
traker.egg-info/dependency_links.txt
traker.egg-info/requires.txt
traker.egg-info/top_level.txt