Metadata-Version: 2.1
Name: traker
Version: 0.3.2
Summary: TRAK: Attributing Model Behavior at Scale
Author: MadryLab
Author-email: trak@mit.edu
Provides-Extra: tests
Provides-Extra: fast
